{"name":"Signing to Straits times","testSteps":[{"number":1,"description":"[1] {ID\u003ddigitaltest1, Password\u003dPassword1}","duration":268,"startTime":1524457535407,"result":"SUCCESS","children":[{"number":2,"description":"Given I have user details for sign in","duration":265,"startTime":1524457535410,"exception":{"errorType":"java.lang.NullPointerException","stackTrace":[{"declaringClass":"com.google.common.base.Preconditions","methodName":"checkNotNull","fileName":"Preconditions.java","lineNumber":210},{"declaringClass":"com.vinoth.test.pages.HomePage","methodName":"verifyPageLoaded","fileName":"HomePage.java","lineNumber":67},{"declaringClass":"com.vinoth.test.steps.SignInScenariosSteps","methodName":"iHaveUserDetailsForSignUpEmailPasswordName","fileName":"SignInScenariosSteps.java","lineNumber":28},{"declaringClass":"✽","methodName":"Given I have user details for sign in","fileName":"src/test/resources/features/SignIn.feature","lineNumber":5}]},"result":"ERROR","children":[{"number":3,"description":"Verify page loaded","duration":0,"startTime":1524457535660,"exception":{"errorType":"java.lang.NullPointerException","stackTrace":[{"declaringClass":"com.google.common.base.Preconditions","methodName":"checkNotNull","fileName":"Preconditions.java","lineNumber":210},{"declaringClass":"com.vinoth.test.pages.HomePage","methodName":"verifyPageLoaded","fileName":"HomePage.java","lineNumber":67},{"declaringClass":"com.vinoth.test.steps.SignInScenariosSteps","methodName":"iHaveUserDetailsForSignUpEmailPasswordName","fileName":"SignInScenariosSteps.java","lineNumber":28}]},"result":"ERROR"}]},{"number":4,"description":"When I click on login digitaltest1 and Password1","duration":0,"startTime":1524457535675,"result":"SKIPPED"},{"number":5,"description":"Then I should be able to see my digitaltest1 account page","duration":0,"startTime":1524457535675,"result":"SKIPPED"}]}],"userStory":{"id":"signing-to-straits-times","storyName":"Signing to Straits times","path":"src/test/resources/features/SignIn.feature","narrative":"As a user i would be able to sign in","type":"feature"},"title":"Signing to Straits times","description":"","tags":[{"name":"Signing to Straits times","type":"feature"}],"startTime":1524457535232,"duration":443,"testFailureCause":{"errorType":"java.lang.NullPointerException","stackTrace":[{"declaringClass":"com.google.common.base.Preconditions","methodName":"checkNotNull","fileName":"Preconditions.java","lineNumber":210},{"declaringClass":"com.vinoth.test.pages.HomePage","methodName":"verifyPageLoaded","fileName":"HomePage.java","lineNumber":67},{"declaringClass":"com.vinoth.test.steps.SignInScenariosSteps","methodName":"iHaveUserDetailsForSignUpEmailPasswordName","fileName":"SignInScenariosSteps.java","lineNumber":28}]},"testFailureClassname":"java.lang.AssertionError","testFailureMessage":"null\r\nnull","annotatedResult":"ERROR","dataTable":{"headers":["ID","Password"],"rows":[{"values":["digitaltest1","Password1"],"result":"ERROR"}],"predefinedRows":true,"dataSetDescriptors":[{"startRow":0,"rowCount":0,"name":"","description":""}]},"manual":false,"result":"ERROR"}